descriptive_uuid_field/__init__.py
descriptive_uuid_field/fields.py
django_descriptive_uuid_field-0.1.0.dist-info/LICENSE.txt
django_descriptive_uuid_field-0.1.0.dist-info/METADATA
django_descriptive_uuid_field-0.1.0.dist-info/WHEEL
django_descriptive_uuid_field-0.1.0.dist-info/top_level.txt
django_descriptive_uuid_field-0.1.0.dist-info/RECORD
